fuzzy_word_map/__init__.py
fuzzy_word_map/fuzzy_word_map.py
fuzzy_word_map-0.0.0.dist-info/METADATA
fuzzy_word_map-0.0.0.dist-info/WHEEL
fuzzy_word_map-0.0.0.dist-info/top_level.txt
fuzzy_word_map-0.0.0.dist-info/RECORD
